soon_kyoo/__init__.py
soon_kyoo/__version__.py
soon_kyoo/broker.py
soon_kyoo/config.py
soon_kyoo/task.py
soon_kyoo/utils.py
soon_kyoo/worker.py
soon_kyoo/cli/__init__.py
soon_kyoo/cli/init_db.py
soon_kyoo/cli/soon_kyoo.py
soon_kyoo/instance/queue.sqlite
soon_kyoo-0.0.4.dist-info/LICENSE
soon_kyoo-0.0.4.dist-info/METADATA
soon_kyoo-0.0.4.dist-info/WHEEL
soon_kyoo-0.0.4.dist-info/entry_points.txt
soon_kyoo-0.0.4.dist-info/top_level.txt
soon_kyoo-0.0.4.dist-info/RECORD
