Metadata-Version: 2.1
Name: soon-kyoo
Version: 0.0.4
Summary: A subprocess-based task queue.
Home-page: https://github.com/n8jhj/soon-kyoo
Author: Nathaniel Jones
Author-email: nathaniel.j.jones@wsu.edu
License: BSD
Platform: UNKNOWN
Classifier: Development Status :: 1 - Planning
Classifier: Environment :: Console
Classifier: Intended Audience :: Developers
Classifier: License :: OSI Approved :: BSD License
Classifier: Operating System :: Microsoft :: Windows
Classifier: Programming Language :: Python
Classifier: Programming Language :: Python :: 3
Classifier: Programming Language :: Python :: 3.6
Classifier: Topic :: Utilities
Requires-Python: >=3.6.0
Requires-Dist: Click
